starter_template/__init__.py
starter_template/actions/__init__.py
starter_template/actions/generate.py
starter_template/configs/__init__.py
starter_template/configs/action_config/generate.yaml
starter_template/configs_tamoyan/__init__.py
starter_template/configs_tamoyan/aim/aim.yaml
starter_template/configs_tamoyan/slurm/no_slurm.yaml
starter_template/configs_tamoyan/slurm/slurm.yaml
urartu/__init__.py
urartu/common/__init__.py
urartu/common/action.py
urartu/common/dataset.py
urartu/common/device.py
urartu/common/metric.py
urartu/common/model.py
urartu/common/pipeline.py
urartu/config/__init__.py
urartu/config/main.yaml
urartu/config/action_config/default_action_config.yaml
urartu/config/aim/default_aim.yaml
urartu/config/machine/local.yaml
urartu/config/machine/remote_machine.yaml
urartu/config/slurm/default_slurm.yaml
urartu/datasets/__init__.py
urartu/datasets/hf/__init__.py
urartu/datasets/hf/dataset_from_dict.py
urartu/datasets/hf/dataset_from_file.py
urartu/datasets/hf/dataset_from_hub.py
urartu/models/__init__.py
urartu/models/model_causal_language.py
urartu/models/model_openai.py
urartu/models/model_pipeline.py
urartu/utils/__init__.py
urartu/utils/dtype.py
urartu/utils/hash.py
urartu/utils/hydra_plugin.py
urartu/utils/job.py
urartu/utils/launcher.py
urartu/utils/logging.py
urartu-4.1.5.dist-info/licenses/LICENSE
urartu-4.1.5.dist-info/licenses/NOTICE
urartu-4.1.5.dist-info/METADATA
urartu-4.1.5.dist-info/WHEEL
urartu-4.1.5.dist-info/entry_points.txt
urartu-4.1.5.dist-info/top_level.txt
urartu-4.1.5.dist-info/RECORD
