Metadata-Version: 2.4
Name: urartu
Version: 4.1.5
Summary: An open-source NLP framework that offers high-level wrappers designed for effortless launch, enhanced reproducibility, superior control, and unmatched flexibility for your experiments.
Requires-Python: >=3.10.0
License-File: LICENSE
License-File: NOTICE
Requires-Dist: hydra-core==1.3.2
Requires-Dist: iopath==0.1.10
Requires-Dist: overrides==7.7.0
Requires-Dist: submitit
Requires-Dist: aim
Requires-Dist: torch
Requires-Dist: datasets
Requires-Dist: transformers
Requires-Dist: evaluate
Requires-Dist: accelerate
Dynamic: description
Dynamic: description-content-type
Dynamic: license-file
Dynamic: requires-dist
Dynamic: requires-python
Dynamic: summary
